tu/__init__.py
tu/__main__.py
tu/cli.py
tu/common.py
tu/utils.py
tu/actions/__init__.py
tu/actions/add.py
tu/actions/backend.py
tu/actions/base.py
tu/actions/config.py
tu/actions/filter.py
tu/actions/read.py
tu/actions/write.py
tu/backends/__init__.py
tu/backends/base.py
tu/backends/dummy.py
tu/backends/ts.py
task_spooler_utils-0.0.9.dist-info/LICENSE.md
task_spooler_utils-0.0.9.dist-info/METADATA
task_spooler_utils-0.0.9.dist-info/WHEEL
task_spooler_utils-0.0.9.dist-info/entry_points.txt
task_spooler_utils-0.0.9.dist-info/top_level.txt
task_spooler_utils-0.0.9.dist-info/RECORD
