Metadata-Version: 2.1
Name: task-spooler-utils
Version: 0.0.9
Summary: A Task Spooler Swiss Army Knife
Author: admk
Project-URL: Homepage, https://github.com/admk/tu
Project-URL: Issues, https://github.com/admk/tu/issues
Classifier: Programming Language :: Python :: 3
Classifier: License :: OSI Approved :: MIT License
Classifier: Operating System :: OS Independent
Requires-Python: >=3.8
License-File: LICENSE.md
Requires-Dist: tqdm
Requires-Dist: tomlkit
Requires-Dist: tabulate >=0.9.0
Requires-Dist: blessed >=1.20.0
